bigjson/__init__.py
bigjson/array.py
bigjson/filereader.py
bigjson/obj.py
bigjson-1.0.9.dist-info/LICENSE
bigjson-1.0.9.dist-info/METADATA
bigjson-1.0.9.dist-info/WHEEL
bigjson-1.0.9.dist-info/top_level.txt
bigjson-1.0.9.dist-info/RECORD
